raspyrfm_client/__init__.py
raspyrfm_client/client.py
raspyrfm_client/device_implementations/__init__.py
raspyrfm_client/device_implementations/manufacturer_constants.py
raspyrfm_client/device_implementations/controlunit/__init__.py
raspyrfm_client/device_implementations/controlunit/actions.py
raspyrfm_client/device_implementations/controlunit/base.py
raspyrfm_client/device_implementations/controlunit/controlunit_constants.py
raspyrfm_client/device_implementations/controlunit/manufacturer/__init__.py
raspyrfm_client/device_implementations/controlunit/manufacturer/bat/RC3500_A_IP44_DE.py
raspyrfm_client/device_implementations/controlunit/manufacturer/bat/RC_AAA1000_A_IP44_Outdoor.py
raspyrfm_client/device_implementations/controlunit/manufacturer/bat/__init__.py
raspyrfm_client/device_implementations/controlunit/manufacturer/brennenstuhl/RCS1000NComfort.py
raspyrfm_client/device_implementations/controlunit/manufacturer/brennenstuhl/RCS1044NComfort.py
raspyrfm_client/device_implementations/controlunit/manufacturer/brennenstuhl/__init__.py
raspyrfm_client/device_implementations/controlunit/manufacturer/elro/AB440D_200W.py
raspyrfm_client/device_implementations/controlunit/manufacturer/elro/AB440D_300W.py
raspyrfm_client/device_implementations/controlunit/manufacturer/elro/AB440ID.py
raspyrfm_client/device_implementations/controlunit/manufacturer/elro/AB440IS.py
raspyrfm_client/device_implementations/controlunit/manufacturer/elro/AB440L.py
raspyrfm_client/device_implementations/controlunit/manufacturer/elro/AB440S.py
raspyrfm_client/device_implementations/controlunit/manufacturer/elro/AB440SC.py
raspyrfm_client/device_implementations/controlunit/manufacturer/elro/AB440WD.py
raspyrfm_client/device_implementations/controlunit/manufacturer/elro/__init__.py
raspyrfm_client/device_implementations/controlunit/manufacturer/hama/_121938.py
raspyrfm_client/device_implementations/controlunit/manufacturer/hama/__init__.py
raspyrfm_client-1.2.8.dist-info/METADATA
raspyrfm_client-1.2.8.dist-info/RECORD
raspyrfm_client-1.2.8.dist-info/WHEEL
raspyrfm_client-1.2.8.dist-info/top_level.txt
