Metadata-Version: 2.1
Name: raspyrfm-client
Version: 1.2.8
Summary: A library to send rc signals with the RaspyRFM module
Home-page: https://github.com/markusressel/raspyrfm-client
Author: Markus Ressel
Author-email: mail@markusressel.de
License: GPLv3+
Platform: UNKNOWN
Classifier: Development Status :: 5 - Production/Stable
Classifier: License :: OSI Approved :: GNU General Public License v3 or later (GPLv3+)
Classifier: Programming Language :: Python :: 3
Classifier: Programming Language :: Python :: 3.4
Classifier: Programming Language :: Python :: 3.5
Classifier: Programming Language :: Python :: 3.6
Classifier: Programming Language :: Python :: 3.7
